MANIFEST.in
README.md
README.rst
setup.py
ulit/__init__.py
ulit/base_service.py
ulit/google.py
ulit/yandex.py
ulit.egg-info/PKG-INFO
ulit.egg-info/SOURCES.txt
ulit.egg-info/dependency_links.txt
ulit.egg-info/requires.txt
ulit.egg-info/top_level.txt
ulit/tests/__init__.py
ulit/tests/test_common.py