Metadata-Version: 1.1
Name: ulit
Version: 0.2.0
Summary: Translate a bunch of times and then see it become funny, almost.
Home-page: https://github.com/amanjeev/ulit
Author: Amanjeev Sethi
Author-email: aj@amanjeev.com
License: MIT
Platform: All
Classifier: Intended Audience :: Developers
Classifier: Operating System :: OS Independent
Classifier: Programming Language :: Python
Classifier: Programming Language :: Python :: 3.4
Provides: ulit
